radariq/RadarIQ.py
radariq/TSerial.py
radariq/__init__.py
radariq/compatability.py
radariq/port_manager.py
radariq/units_converter.py
radariq-1.0.7.dist-info/METADATA
radariq-1.0.7.dist-info/WHEEL
radariq-1.0.7.dist-info/licenses/LICENCE
radariq-1.0.7.dist-info/RECORD
