Metadata-Version: 2.1
Name: radariq
Version: 1.0.7
Summary: Python SDK for the RadarIQ sensor
Author-email: RadarIQ Ltd <support@radariq.io>
License-File: LICENCE
Classifier: Development Status :: 4 - Beta
Classifier: Intended Audience :: Developers
Classifier: License :: OSI Approved :: MIT License
Classifier: Natural Language :: English
Classifier: Operating System :: OS Independent
Classifier: Programming Language :: Python :: 2
Classifier: Programming Language :: Python :: 3
Classifier: Topic :: System :: Hardware :: Hardware Drivers
Requires-Python: >=2.7
